aa_whisper-0.1.0.dist-info/licenses/LICENSE
whisper/__init__.py
whisper/main.py
aa_whisper-0.1.0.dist-info/METADATA
aa_whisper-0.1.0.dist-info/WHEEL
aa_whisper-0.1.0.dist-info/entry_points.txt
aa_whisper-0.1.0.dist-info/top_level.txt
aa_whisper-0.1.0.dist-info/RECORD
