Metadata-Version: 2.4
Name: aa-whisper
Version: 0.1.0
Summary: A simple pip template by Abdullah Adeeb
Author-email: Abdullah Adeeb <abdullah@abdullahadeeb.xyz>
License-Expression: MIT
Project-URL: Repository, https://github.com/abdullahadeebx/whisper
Project-URL: Bug Tracker, https://github.com/abdullahadeebx/whisper/issues
Project-URL: Homepage, https://www.abdullahadeeb.xyz
Keywords: pip,template,cli
Classifier: Development Status :: 5 - Production/Stable
Classifier: Intended Audience :: Developers
Classifier: Programming Language :: Python :: 3
Classifier: Programming Language :: Python :: 3.7
Classifier: Programming Language :: Python :: 3.8
Classifier: Programming Language :: Python :: 3.9
Classifier: Programming Language :: Python :: 3.10
Classifier: Programming Language :: Python :: 3.11
Classifier: Programming Language :: Python :: 3.12
Classifier: Programming Language :: Python :: 3.13
Classifier: Operating System :: OS Independent
Classifier: Topic :: Utilities
Requires-Python: >=3.7
License-File: LICENSE
Requires-Dist: requests>=2.25.0
Requires-Dist: python-dotenv>=0.15.0
Requires-Dist: pyperclip>=1.8.0
Requires-Dist: ffmpeg-python>=0.2.0
Dynamic: license-file
